odoo/addons/pos_order_taxes_fix/__init__.py
odoo/addons/pos_order_taxes_fix/__manifest__.py
odoo/addons/pos_order_taxes_fix/models/__init__.py
odoo/addons/pos_order_taxes_fix/models/pos_session.py
odoo/addons/pos_order_taxes_fix/views/pos_session_view.xml
odoo12_addon_pos_order_taxes_fix-12.0.1.0.0.99.dev3.dist-info/METADATA
odoo12_addon_pos_order_taxes_fix-12.0.1.0.0.99.dev3.dist-info/WHEEL
odoo12_addon_pos_order_taxes_fix-12.0.1.0.0.99.dev3.dist-info/top_level.txt
odoo12_addon_pos_order_taxes_fix-12.0.1.0.0.99.dev3.dist-info/RECORD
