Metadata-Version: 2.1
Name: odoo12-addon-pos-order-taxes-fix
Version: 12.0.1.0.0.99.dev3
Summary: Adds a button to on pos session to fix the taxes of the orders that doesn't match the calculation on backend"
Home-page: https://coopiteasy.be
Author: Coop IT Easy SCRL fs
License: UNKNOWN
Platform: UNKNOWN
Classifier: Programming Language :: Python
Classifier: Framework :: Odoo
Requires-Python: >=3.5
Requires-Dist: odoo (<12.1dev,>=12.0a)
